MANIFEST.in
README.md
requirements.txt
setup.cfg
setup.py
profanity_police/__init__.py
profanity_police/checker.py
profanity_police/data.py
profanity_police/exceptions.py
profanity_police/srt_extractor.py
profanity_police/transcript_checker.py
profanity_police/txt_extractor.py
profanity_police/youtube.py
profanity_police.egg-info/PKG-INFO
profanity_police.egg-info/SOURCES.txt
profanity_police.egg-info/dependency_links.txt
profanity_police.egg-info/not-zip-safe
profanity_police.egg-info/requires.txt
profanity_police.egg-info/top_level.txt