Metadata-Version: 2.1
Name: profanity-police
Version: 1.0.0
Summary: This is a python API which allows you to check for swear words in a youtube video, srt file, text file, custom source with multi language support. There are additional features like getting youtube transcript of a video, srt parser etc.
Home-page: https://github.com/vivekkumar2696/profanity-police
Author: Vivek Kamal Kumar
Author-email: kumar.vivek2696@gmail.com
License: MIT
Keywords: transcript,profanity,profanity-detection,swearword,srt-parser,youtube-transcripts,youtube-captions
Platform: UNKNOWN
Classifier: Development Status :: 3 - Alpha
Classifier: Intended Audience :: Developers
Classifier: Topic :: Software Development :: Build Tools
Classifier: License :: OSI Approved :: MIT License
Classifier: Programming Language :: Python :: 3
Classifier: Programming Language :: Python :: 3.4
Classifier: Programming Language :: Python :: 3.5
Classifier: Programming Language :: Python :: 3.6
Classifier: Programming Language :: Python :: 3.7
Classifier: Programming Language :: Python :: 3.8
